MANIFEST.in
README.rst
setup.py
docs/HISTORY.txt
docs/LICENSE.GPL
docs/LICENSE.txt
ftw/__init__.py
ftw.servicenavigation.egg-info/PKG-INFO
ftw.servicenavigation.egg-info/SOURCES.txt
ftw.servicenavigation.egg-info/dependency_links.txt
ftw.servicenavigation.egg-info/entry_points.txt
ftw.servicenavigation.egg-info/namespace_packages.txt
ftw.servicenavigation.egg-info/not-zip-safe
ftw.servicenavigation.egg-info/requires.txt
ftw.servicenavigation.egg-info/top_level.txt
ftw/servicenavigation/__init__.py
ftw/servicenavigation/configure.zcml
ftw/servicenavigation/form.py
ftw/servicenavigation/interfaces.py
ftw/servicenavigation/lawgiver.zcml
ftw/servicenavigation/mobile_button.py
ftw/servicenavigation/permissions.zcml
ftw/servicenavigation/profiles.zcml
ftw/servicenavigation/testing.py
ftw/servicenavigation/viewlet.py
ftw/servicenavigation/Extensions/install.py
ftw/servicenavigation/locales/ftw.servicenavigation-manual.pot
ftw/servicenavigation/locales/ftw.servicenavigation.pot
ftw/servicenavigation/locales/de/LC_MESSAGES/ftw.servicenavigation.po
ftw/servicenavigation/locales/en/LC_MESSAGES/ftw.servicenavigation.po
ftw/servicenavigation/locales/fr/LC_MESSAGES/ftw.servicenavigation.po
ftw/servicenavigation/locales/it/LC_MESSAGES/ftw.servicenavigation.po
ftw/servicenavigation/profiles/default/browserlayer.xml
ftw/servicenavigation/profiles/default/cssregistry.xml
ftw/servicenavigation/profiles/default/jsregistry.xml
ftw/servicenavigation/profiles/default/metadata.xml
ftw/servicenavigation/profiles/default/rolemap.xml
ftw/servicenavigation/profiles/default/viewlets.xml
ftw/servicenavigation/profiles/default_plone5/browserlayer.xml
ftw/servicenavigation/profiles/default_plone5/metadata.xml
ftw/servicenavigation/profiles/default_plone5/registry.xml
ftw/servicenavigation/profiles/default_plone5/rolemap.xml
ftw/servicenavigation/profiles/default_plone5/viewlets.xml
ftw/servicenavigation/profiles/uninstall/browserlayer.xml
ftw/servicenavigation/profiles/uninstall/cssregistry.xml
ftw/servicenavigation/profiles/uninstall/jsregistry.xml
ftw/servicenavigation/profiles/uninstall/rolemap.xml
ftw/servicenavigation/profiles/uninstall/viewlets.xml
ftw/servicenavigation/profiles/uninstall_plone5/browserlayer.xml
ftw/servicenavigation/profiles/uninstall_plone5/registry.xml
ftw/servicenavigation/profiles/uninstall_plone5/rolemap.xml
